keras_explain/__init__.py
keras_explain/fong.py
keras_explain/grad_cam.py
keras_explain/graying_out.py
keras_explain/guided_bp.py
keras_explain/integrated_gradients.py
keras_explain/lime_ribeiro.py
keras_explain/lrp.py
keras_explain/prediction_diff.py
keras_explain/saliency.py
keras_explain/deep_viz_keras/__init__.py
keras_explain/deep_viz_keras/guided_backprop.py
keras_explain/deep_viz_keras/integrated_gradients.py
keras_explain/deep_viz_keras/saliency.py
keras_explain/deep_viz_keras/utils.py
keras_explain/deep_viz_keras/visual_backprop.py
keras_explain/zintgraf_utils/__init__.py
keras_explain/zintgraf_utils/prediction_difference_analysis.py
keras_explain/zintgraf_utils/utils_sampling.py
keras_explain-0.0.1.dist-info/METADATA
keras_explain-0.0.1.dist-info/RECORD
keras_explain-0.0.1.dist-info/WHEEL
keras_explain-0.0.1.dist-info/top_level.txt
test/__init__.py
test/test_images.py
