Metadata-Version: 2.1
Name: keras-explain
Version: 0.0.1
Summary: Explanation toolbox for Keras models. 
Home-page: https://github.com/primozgodec/keras-explain
Author: Primoz Godec
Author-email: primoz492@gmail.com
License: UNKNOWN
Platform: UNKNOWN
Classifier: Programming Language :: Python :: 3
Classifier: License :: OSI Approved :: MIT License
Classifier: Operating System :: OS Independent
Requires-Dist: Keras (==2.1.6)
Requires-Dist: Pillow
Requires-Dist: keras-vis-temp
Requires-Dist: lime
Requires-Dist: pytest
